{
  "coverTypes": {
    "type1": {
      "name": {
        "en": "Preset Cover 1",
        "ru": "Шаблон обложки 1"
      },
      "imageFolder": "./img/",
      "logoPositioningParams": {
        "upperBound": 377.5,
        "verticalOffset": 223,
        "maxWidth": 500,
        "maxHeight": 145
      },
      "backgroundImage": "Bgiconsize.png",
      "topLayerImage": "Toplayer.png"
    },
    "type2": {
      "name": {
        "en": "Preset Cover 2",
        "ru": "Шаблон обложки 2"
      },
      "imageFolder": "./img2/",
      "logoPositioningParams": {
        "upperBound": 350,
        "verticalOffset": 180,
        "maxWidth": 500,
        "maxHeight": 200
      },
      "backgroundImage": "Bgiconsize.png",
      "topLayerImage": "Toplayer.png"
    },
    "custom": {
      "name": {
        "en": "Custom Cover",
        "ru": "Пользовательская обложка"
      },
      "imageFolder": "",
      "logoPositioningParams": {
        "upperBound": 300,
        "verticalOffset": 0,
        "maxWidth": 600,
        "maxHeight": 300
      },
      "requiresUserLayers": true
    }
  },
  "defaultSettings": {
    "canvas": {
      "width": 600,
      "height": 900
    },
    "filters": {
      "options": [
        {
          "id": "none",
          "name": {
            "en": "No Filter",
            "ru": "Без фильтра"
          }
        },
        {
          "id": "red",
          "name": {
            "en": "Red",
            "ru": "Красный"
          },
          "color": "rgba(255, 0, 0, $opacity)"
        },
        {
          "id": "green",
          "name": {
            "en": "Green",
            "ru": "Зелёный"
          },
          "color": "rgba(0, 255, 0, $opacity)"
        },
        {
          "id": "blue",
          "name": {
            "en": "Blue",
            "ru": "Синий"
          },
          "color": "rgba(0, 0, 255, $opacity)"
        },
        {
          "id": "yellow",
          "name": {
            "en": "Yellow",
            "ru": "Жёлтый"
          },
          "color": "rgba(255, 255, 0, $opacity)"
        },
        {
          "id": "purple",
          "name": {
            "en": "Purple",
            "ru": "Пурпурный"
          },
          "color": "rgba(128, 0, 128, $opacity)"
        },
        {
          "id": "orange",
          "name": {
            "en": "Orange",
            "ru": "Оранжевый"
          },
          "color": "rgba(255, 165, 0, $opacity)"
        },
        {
          "id": "custom",
          "name": {
            "en": "Custom",
            "ru": "Пользовательский"
          }
        }
      ],
      "blendModes": [
        {
          "id": "multiply",
          "name": {
            "en": "Multiply",
            "ru": "Умножение"
          }
        },
        {
          "id": "screen",
          "name": {
            "en": "Screen",
            "ru": "Экран"
          }
        },
        {
          "id": "overlay",
          "name": {
            "en": "Overlay",
            "ru": "Перекрытие"
          }
        },
        {
          "id": "color",
          "name": {
            "en": "Color",
            "ru": "Цвет"
          }
        },
        {
          "id": "hue",
          "name": {
            "en": "Hue",
            "ru": "Тон"
          }
        },
        {
          "id": "saturation",
          "name": {
            "en": "Saturation",
            "ru": "Насыщенность"
          }
        },
        {
          "id": "soft-light",
          "name": {
            "en": "Soft Light",
            "ru": "Мягкий свет"
          }
        }
      ],
      "defaultIntensity": 0.7,
      "defaultBlendMode": "multiply",
      "defaultCustomColor": "#ff0000"
    },
    "logo": {
      "blendModes": [
        {
          "id": "normal",
          "name": {
            "en": "Normal",
            "ru": "Обычный"
          }
        },
        {
          "id": "multiply",
          "name": {
            "en": "Multiply",
            "ru": "Умножение"
          }
        },
        {
          "id": "screen",
          "name": {
            "en": "Screen",
            "ru": "Экран"
          }
        },
        {
          "id": "overlay",
          "name": {
            "en": "Overlay",
            "ru": "Перекрытие"
          }
        },
        {
          "id": "darken",
          "name": {
            "en": "Darken",
            "ru": "Затемнение"
          }
        },
        {
          "id": "lighten",
          "name": {
            "en": "Lighten",
            "ru": "Осветление"
          }
        },
        {
          "id": "color-dodge",
          "name": {
            "en": "Color Dodge",
            "ru": "Осветление основы"
          }
        },
        {
          "id": "color-burn",
          "name": {
            "en": "Color Burn",
            "ru": "Затемнение основы"
          }
        },
        {
          "id": "hard-light",
          "name": {
            "en": "Hard Light",
            "ru": "Жёсткий свет"
          }
        },
        {
          "id": "soft-light",
          "name": {
            "en": "Soft Light",
            "ru": "Мягкий свет"
          }
        },
        {
          "id": "difference",
          "name": {
            "en": "Difference",
            "ru": "Разница"
          }
        },
        {
          "id": "exclusion",
          "name": {
            "en": "Exclusion",
            "ru": "Исключение"
          }
        },
        {
          "id": "hue",
          "name": {
            "en": "Hue",
            "ru": "Тон"
          }
        },
        {
          "id": "saturation",
          "name": {
            "en": "Saturation",
            "ru": "Насыщенность"
          }
        },
        {
          "id": "color",
          "name": {
            "en": "Color",
            "ru": "Цвет"
          }
        },
        {
          "id": "luminosity",
          "name": {
            "en": "Luminosity",
            "ru": "Светимость"
          }
        }
      ],
      "defaultOpacity": 1.0,
      "defaultScale": 1.0,
      "defaultColor": "#000000",
      "defaultBlendMode": "normal",
      "defaultIntensity": 1.0,
      "shadowOpacity": 0.3,
      "shadowBlur": 39,
      "shadowColor": "rgba(0, 0, 0, 0.3)",
      "shadowOffsetX": 0,
      "shadowOffsetY": 0
    },
    "images": {
      "maxScale": 0.8,
      "defaultOpacity": 1.0
    }
  }
}
